{
  "id": "durga_saptashati_chapter_9_sloka_5",
  "source": "Durga Saptashati / Devi Mahatmyam",
  "chapter": "9",
  "sloka_number": "5",
  "source_citation": "",
  "sloka_original": "చకార కోపమతులం రక్తబీజే నిపాతితే।\nశుంభాసురో నిశుంభశ్చ హతేష్వన్యేషు చాహవే || 5 ||",
  "pada_vibhaga": [
    {
      "word": "చకార",
      "meaning": "చేశాడు / పొందాడు",
      "grammar": "కృ ధాతువు, లిట్ లకారం, ప్రథమ పురుష, ఏకవచనం"
    },
    {
      "word": "కోపమ్",
      "meaning": "కోపాన్ని",
      "grammar": "ద్వితీయా విభక్తి, ఏకవచనం, పుంలింగం"
    },
    {
      "word": "అతులమ్",
      "meaning": "సాటిలేని",
      "grammar": "ద్వితీయా విభక్తి, ఏకవచనం, పుంలింగం"
    },
    {
      "word": "రక్తబీజే",
      "meaning": "రక్తబీజుడు",
      "grammar": "సప్తమీ విభక్తి, ఏకవచనం, పుంలింగం"
    },
    {
      "word": "నిపాతితే",
      "meaning": "పడగొట్టబడినప్పుడు",
      "grammar": "సప్తమీ ఏకవచన కృదంతం"
    },
    {
      "word": "శుంభాసురః",
      "meaning": "శుంభాసురుడు",
      "grammar": "ప్రథమా విభక్తి, ఏకవచనం, పుంలింగం"
    },
    {
      "word": "నిశుంభః",
      "meaning": "నిశుంభుడు",
      "grammar": "ప్రథమా విభక్తి, ఏకవచనం, పుంలింగం"
    },
    {
      "word": "చ",
      "meaning": "మరియు",
      "grammar": "అవ్యయం"
    },
    {
      "word": "హతేషు",
      "meaning": "చంపబడిన వారిలో / చంపబడినప్పుడు",
      "grammar": "సప్తమీ విభక్తి, బహువచనం"
    },
    {
      "word": "అన్యేషు",
      "meaning": "ఇతరులలో",
      "grammar": "సప్తమీ విభక్తి, బహువచనం"
    },
    {
      "word": "చ",
      "meaning": "కూడా",
      "grammar": "అవ్యయం"
    },
    {
      "word": "ఆహవే",
      "meaning": "యుద్ధంలో",
      "grammar": "సప్తమీ విభక్తి, ఏకవచనం, పుంలింగం"
    }
  ],
  "anvaya": "రక్తబీజే నిపాతితే, ఆహవే ఇతరేషు చ హతేషు, శుంభాసురః నిశుంభః చ అతులం కోపం చకార।",
  "tatparyam": {
    "english": "When Raktabīja had fallen and the other demons too were slain in battle, Śumbha and Niśumbha became filled with incomparable anger.",
    "telugu": "రక్తబీజుడు పడగొట్టబడినప్పుడు, యుద్ధంలో ఇతర అసురులూ హతులైనప్పుడు, శుంభాసురుడు మరియు నిశుంభుడు అపారమైన కోపాన్ని పొందారు."
  },
  "samasas": [
    {
      "compound": "శుంభాసురః",
      "type": "కర్మధారయ సమాసం — శుంభః అసురః"
    }
  ],
  "sandhis": [
    {
      "joined_word": "కోపమతులమ్",
      "split_words": "కోపమ్ + అతులమ్",
      "sandhi_rule": "అనుస్వార/మకార సంయోగం — పదాంత మ్ తరువాత స్వరం రావడంతో సంయుక్తోచ్చారణ."
    },
    {
      "joined_word": "శుంభాసురః",
      "split_words": "శుంభ + అసురః",
      "sandhi_rule": "సవర్ణదీర్ఘ స్వరసంధి — అ + అ → ఆ"
    },
    {
      "joined_word": "నిశుంభశ్చ",
      "split_words": "నిశుంభః + చ",
      "sandhi_rule": "విసర్గసంధి — ః + చ → శ్చ"
    },
    {
      "joined_word": "హతేష్వన్యేషు",
      "split_words": "హతేషు + అన్యేషు",
      "sandhi_rule": "యణ్ సంధి — ఉ + అ → వ"
    },
    {
      "joined_word": "చాహవే",
      "split_words": "చ + ఆహవే",
      "sandhi_rule": "సవర్ణదీర్ఘ స్వరసంధి — అ + ఆ → ఆ"
    }
  ],
  "alamkaram_chandas": "అనుష్టుప్ ఛందస్సు. ‘అతులం కోపం’లో అతిశయోక్తి భావం ఉంది."
}