{
  "id": "durga_saptashati_1_22",
  "source": "Durga Saptashati - Chapter 1",
  "chapter": 1,
  "sloka_number": 22,
  "sloka_original": "పుత్రదారైర్నిరస్తశ్చ ధనలోభాదసాధుభిః| \nవిహీనశ్చ ధనైర్దారైః పుత్రైరాదాయ మే ధనమ్ || 22 ||",
  "pada_vibhaga": [
    {
      "word": "పుత్రదారైః",
      "meaning": "కొడుకులు మరియు భార్యచేత",
      "grammar": "ద్వంద్వ సమాస పదం, తృతీయా విభక్తి, బహువచనం, పుంలింగం"
    },
    {
      "word": "నిరస్తః",
      "meaning": "తొలగించబడినవాడు, బయటకు పంపబడినవాడు",
      "grammar": "నిర్ + అస् ధాతు భావం, క్త కృదంతం, ప్రథమా విభక్తి, ఏకవచనం, పుంలింగం"
    },
    {
      "word": "చ",
      "meaning": "మరియు",
      "grammar": "అవ్యయం"
    },
    {
      "word": "ధనలోభాత్",
      "meaning": "ధనంపై లోభం వలన",
      "grammar": "సమాస పదం, పంచమీ విభక్తి, ఏకవచనం, పుంలింగం"
    },
    {
      "word": "అసాధుభిః",
      "meaning": "దుష్టులచేత, సజ్జనులు కానివారిచేత",
      "grammar": "అసాధు శబ్దం, తృతీయా విభక్తి, బహువచనం, పుంలింగం"
    },
    {
      "word": "విహీనః",
      "meaning": "విడిచిపెట్టబడ్డవాడు, కోల్పోయినవాడు",
      "grammar": "వి + హా ధాతు భావం, క్త కృదంతం, ప్రథమా విభక్తి, ఏకవచనం, పుంలింగం"
    },
    {
      "word": "చ",
      "meaning": "మరియు",
      "grammar": "అవ్యయం"
    },
    {
      "word": "ధనైః",
      "meaning": "ధనములతో, సంపదలతో",
      "grammar": "ధన శబ్దం, తృతీయా విభక్తి, బహువచనం, నపుంసకలింగం"
    },
    {
      "word": "దారైః",
      "meaning": "భార్యచేత లేదా భార్యలచేత",
      "grammar": "దార శబ్దం, తృతీయా విభక్తి, బహువచనం, పుంలింగం"
    },
    {
      "word": "పుత్రైః",
      "meaning": "పుత్రులచేత",
      "grammar": "పుత్ర శబ్దం, తృతీయా విభక్తి, బహువచనం, పుంలింగం"
    },
    {
      "word": "ఆదాయ",
      "meaning": "తీసుకొని",
      "grammar": "ఆ + దా ధాతువు, ల్యబ్ అవ్యయం"
    },
    {
      "word": "మే",
      "meaning": "నా",
      "grammar": "అస్మద్ శబ్దం, షష్ఠీ విభక్తి, ఏకవచనం"
    },
    {
      "word": "ధనమ్",
      "meaning": "ధనాన్ని",
      "grammar": "ధన శబ్దం, ద్వితీయా విభక్తి, ఏకవచనం, నపుంసకలింగం"
    }
  ],
  "anvaya": "అసాధుభిః పుత్రదారైః ధనలోభాత్ మే ధనం ఆదాయ అహం నిరస్తః చ ధనైః దారైః పుత్రైః విహీనః చ.",
  "tatparyam": {
    "english": "Because of greed for wealth, my wicked sons and wife took my money and cast me out. I have been deprived of wealth, wife, and sons.",
    "telugu": "ధనలోభంతో దుష్టులైన నా పుత్రులు మరియు భార్య నా ధనాన్ని తీసుకొని నన్ను ఇంటి నుండి తొలగించారు. నేను ధనం, భార్య, పుత్రులు అన్నిటి నుండి విహీనుడనయ్యాను."
  },
  "samasas": [
    {
      "compound": "పుత్రదారైః",
      "type": "ద్వంద్వ సమాసం"
    },
    {
      "compound": "ధనలోభాత్",
      "type": "షష్ఠీ తత్పురుష సమాసం"
    }
  ],
  "sandhis": [
    {
      "joined_word": "పుత్రదారైర్నిరస్తః",
      "split_words": "పుత్రదారైః + నిరస్తః",
      "sandhi_rule": "విసర్గ సంధి"
    },
    {
      "joined_word": "నిరస్తశ్చ",
      "split_words": "నిరస్తః + చ",
      "sandhi_rule": "విసర్గ సంధి"
    },
    {
      "joined_word": "ధనలోభాదసాధుభిః",
      "split_words": "ధనలోభాత్ + అసాధుభిః",
      "sandhi_rule": "జశ్త్వ/వ్యంజన సంధి"
    },
    {
      "joined_word": "విహీనశ్చ",
      "split_words": "విహీనః + చ",
      "sandhi_rule": "విసర్గ సంధి"
    },
    {
      "joined_word": "ధనైర్దారైః",
      "split_words": "ధనైః + దారైః",
      "sandhi_rule": "విసర్గ సంధి"
    },
    {
      "joined_word": "పుత్రైరాదాయ",
      "split_words": "పుత్రైః + ఆదాయ",
      "sandhi_rule": "విసర్గ సంధి"
    }
  ],
  "alamkaram_chandas": "Chandas: అనుష్టుప్ (Anuṣṭup)."
}