{
  "id": "durga_saptashati_chapter_5_sloka_82",
  "source": "Durga Saptashati / Devi Mahatmyam",
  "chapter": "5",
  "sloka_number": "82",
  "source_citation": "",
  "sloka_original": "యా సాంప్రతం చోద్ధతదైత్యతాపితై\nరస్మాభిరీశా చ సురైర్నమస్యతే।\nయా చ స్మృతా తత్క్షణమేవ హంతి నః\nసర్వాపదో భక్తివినమ్రమూర్తిభిః || 82 ||",
  "pada_vibhaga": [
    {
      "word": "యా",
      "meaning": "యావిడ",
      "grammar": "ప్రథమా విభక్తి, ఏకవచనం, స్త్రీలింగం"
    },
    {
      "word": "సాంప్రతమ్",
      "meaning": "ఇప్పుడు",
      "grammar": "అవ్యయం"
    },
    {
      "word": "చ",
      "meaning": "మరియు",
      "grammar": "అవ్యయం"
    },
    {
      "word": "ఉద్ధతదైత్యతాపితైః",
      "meaning": "ఉద్ధతమైన దైత్యులచేత బాధింపబడినవారిచేత",
      "grammar": "తృతీయా విభక్తి, బహువచనం, పుంలింగం"
    },
    {
      "word": "అస్మాభిః",
      "meaning": "మాచేత",
      "grammar": "తృతీయా విభక్తి, బహువచనం, అస్మద్ శబ్దం"
    },
    {
      "word": "ఈశా",
      "meaning": "ఈశ్వరి",
      "grammar": "ప్రథమా విభక్తి, ఏకవచనం, స్త్రీలింగం"
    },
    {
      "word": "సురైః",
      "meaning": "దేవతలచేత",
      "grammar": "తృతీయా విభక్తి, బహువచనం, పుంలింగం"
    },
    {
      "word": "నమస్యతే",
      "meaning": "నమస్కరింపబడుచున్నది",
      "grammar": "నమస్ ధాతువు, లట్ లకారం, కర్మణి, ప్రథమ పురుషం, ఏకవచనం"
    },
    {
      "word": "స్మృతా",
      "meaning": "స్మరింపబడినది",
      "grammar": "స్మృ ధాతువు, క్త ప్రత్యయాంతం, ప్రథమా ఏకవచనం, స్త్రీలింగం"
    },
    {
      "word": "తత్‌క్షణమ్",
      "meaning": "ఆ క్షణంలోనే",
      "grammar": "ద్వితీయా విభక్తి, ఏకవచనం, కాలవాచక అవ్యయప్రయోగం"
    },
    {
      "word": "ఏవ",
      "meaning": "నిశ్చయంగా",
      "grammar": "అవ్యయం"
    },
    {
      "word": "హంతి",
      "meaning": "నశింపజేయును",
      "grammar": "హన్ ధాతువు, లట్ లకారం, ప్రథమ పురుషం, ఏకవచనం"
    },
    {
      "word": "నః",
      "meaning": "మా",
      "grammar": "షష్ఠీ విభక్తి, బహువచనం, అస్మద్ శబ్దం"
    },
    {
      "word": "సర్వాపదః",
      "meaning": "సమస్త ఆపదలను",
      "grammar": "ద్వితీయా విభక్తి, బహువచనం, స్త్రీలింగం"
    },
    {
      "word": "భక్తివినమ్రమూర్తిభిః",
      "meaning": "భక్తిచేత వినమ్రమైన రూపములుగల మాచేత",
      "grammar": "తృతీయా విభక్తి, బహువచనం, పుంలింగం"
    }
  ],
  "anvaya": "యా ఈశా సాంప్రతం ఉద్ధతదైత్యతాపితైః అస్మాభిః సురైః భక్తివినమ్రమూర్తిభిః నమస్యతే, యా చ స్మృతా తత్‌క్షణమ్ ఏవ నః సర్వాపదః హంతి।",
  "tatparyam": {
    "english": "That sovereign Goddess is now worshipped by us gods, afflicted by arrogant demons and bowed down in devotion. When remembered, she destroys all our calamities at that very moment.",
    "telugu": "ఉద్ధత దైత్యులచేత బాధింపబడి, భక్తితో వినమ్రులమైన మేము దేవతలు ఇప్పుడు ఆ ఈశ్వరిని నమస్కరిస్తున్నాము. ఆమె స్మరింపబడగానే ఆ క్షణమే మా సమస్త ఆపదలను నశింపజేస్తుంది."
  },
  "samasas": [
    {
      "compound": "ఉద్ధతదైత్యతాపితైః",
      "type": "తృతీయా తత్పురుషగర్భిత బహువ్రీహి — ఉద్ధతైః దైత్యైః తాపితాః యే"
    },
    {
      "compound": "తత్‌క్షణమ్",
      "type": "కర్మధారయ సమాసం — సః క్షణః"
    },
    {
      "compound": "సర్వాపదః",
      "type": "కర్మధారయ సమాసం — సర్వాః ఆపదః"
    },
    {
      "compound": "భక్తివినమ్రమూర్తిభిః",
      "type": "తృతీయా తత్పురుషగర్భిత బహువ్రీహి — భక్త్యా వినమ్రా మూర్తిః యేషాం తైః"
    }
  ],
  "sandhis": [
    {
      "joined_word": "చోద్ధతదైత్యతాపితైః",
      "split_words": "చ + ఉద్ధతదైత్యతాపితైః",
      "sandhi_rule": "గుణ సంధి — అ + ఉ = ఓ"
    },
    {
      "joined_word": "తాపితైరస్మాభిః",
      "split_words": "తాపితైః + అస్మాభిః",
      "sandhi_rule": "విసర్గ సంధి — ఐః + అ సందర్భంలో ర్ ఆదేశం"
    },
    {
      "joined_word": "సురైర్నమస్యతే",
      "split_words": "సురైః + నమస్యతే",
      "sandhi_rule": "విసర్గ సంధి — ఐః తరువాత న్ వచ్చినప్పుడు ర్ రూపం"
    },
    {
      "joined_word": "తత్క్షణమేవ",
      "split_words": "తత్‌క్షణమ్ + ఏవ",
      "sandhi_rule": "పదాంత మ్ సంధి — మ్ తరువాత స్వరం వచ్చినందున అనుసంధానం"
    }
  ],
  "alamkaram_chandas": "ఉపజాతి/త్రిష్టుప్ శైలి. దేవి స్మరణమాత్రఫలాన్ని బలంగా చెప్పుట వలన భక్తిరసప్రధాన పునరుక్తి భావం ఉంది."
}