{
  "id": "durga_saptashati_chapter_6_sloka_19",
  "source": "Durga Saptashati / Devi Mahatmyam",
  "chapter": "6",
  "sloka_number": "19",
  "source_citation": "",
  "sloka_original": "క్షణేన తద్బలం సర్వం క్షయం నీతం మహాత్మనా।\nతేన కేసరిణా దేవ్యా వాహనేనాతికోపినా || 19 ||",
  "pada_vibhaga": [
    {
      "word": "క్షణేన",
      "meaning": "క్షణములోనే",
      "grammar": "తృతీయా విభక్తి, ఏకవచనం, పుంలింగం; కాలవాచక ప్రయోగం"
    },
    {
      "word": "తత్",
      "meaning": "ఆ",
      "grammar": "సర్వనామ విశేషణం, నపుంసకలింగం, ఏకవచనం"
    },
    {
      "word": "బలమ్",
      "meaning": "సైన్యము",
      "grammar": "ప్రథమా/ద్వితీయా విభక్తి, ఏకవచనం, నపుంసకలింగం; ఇక్కడ కర్మార్థం"
    },
    {
      "word": "సర్వమ్",
      "meaning": "మొత్తము",
      "grammar": "ద్వితీయా విభక్తి, ఏకవచనం, నపుంసకలింగం"
    },
    {
      "word": "క్షయమ్",
      "meaning": "నాశనాన్ని",
      "grammar": "ద్వితీయా విభక్తి, ఏకవచనం, పుంలింగం"
    },
    {
      "word": "నీతమ్",
      "meaning": "తీసుకుపోబడింది, చేర్చబడింది",
      "grammar": "క్తప్రత్యయాంతం, ప్రథమా/ద్వితీయా విభక్తి, ఏకవచనం, నపుంసకలింగం"
    },
    {
      "word": "మహాత్మనా",
      "meaning": "మహాత్ముడైన",
      "grammar": "తృతీయా విభక్తి, ఏకవచనం, పుంలింగం"
    },
    {
      "word": "తేన",
      "meaning": "ఆ",
      "grammar": "తృతీయా విభక్తి, ఏకవచనం, పుంలింగ సర్వనామం"
    },
    {
      "word": "కేసరిణా",
      "meaning": "సింహముచేత",
      "grammar": "తృతీయా విభక్తి, ఏకవచనం, పుంలింగం"
    },
    {
      "word": "దేవ్యాః",
      "meaning": "దేవి యొక్క",
      "grammar": "షష్ఠీ విభక్తి, ఏకవచనం, స్త్రీలింగం"
    },
    {
      "word": "వాహనేన",
      "meaning": "వాహనముచేత",
      "grammar": "తృతీయా విభక్తి, ఏకవచనం, నపుంసకలింగం"
    },
    {
      "word": "అతికోపినా",
      "meaning": "అత్యంత కోపగలవాడైన",
      "grammar": "తృతీయా విభక్తి, ఏకవచనం, పుంలింగం"
    }
  ],
  "anvaya": "క్షణేన దేవ్యాః వాహనేన అతికోపినా తేన మహాత్మనా కేసరిణా తత్ సర్వం బలం క్షయం నీతమ్।",
  "tatparyam": {
    "english": "In a moment, that entire army was brought to destruction by that noble lion, the Goddess’s vehicle, who was exceedingly enraged.",
    "telugu": "క్షణములోనే, దేవి వాహనమైన ఆ మహాత్ముడైన సింహము అత్యంత కోపంతో ఆ సర్వ సైన్యాన్ని నాశనానికి గురిచేసింది."
  },
  "samasas": [
    {
      "compound": "తద్బలం",
      "type": "కర్మధారయ సమాసం — తత్ బలం"
    },
    {
      "compound": "మహాత్మనా",
      "type": "బహువ్రీహి సమాసం — మహాన్ ఆత్మా యస్య సః, తేన"
    },
    {
      "compound": "అతికోపినా",
      "type": "అవ్యయీభావ/కర్మధారయ సమాససదృశం — అతిశయేన కోపీ, తేన"
    }
  ],
  "sandhis": [
    {
      "joined_word": "తద్బలం",
      "split_words": "తత్ + బలం",
      "sandhi_rule": "జశ్త్వ సంధి — త్ + బ వద్ద త్ కు ద్ ఆదేశం."
    },
    {
      "joined_word": "వాహనేనాతికోపినా",
      "split_words": "వాహనేన + అతికోపినా",
      "sandhi_rule": "సవర్ణ దీర్ఘ సంధి — అ + అ = ఆ; న + అ పదసంధి."
    }
  ],
  "alamkaram_chandas": "అనుష్టుప్ ఛందస్సు. క్షణేన అనే కాలసూచనతో సింహబల అతిశయము వ్యక్తమై వీరరసము ప్రధానమవుతుంది."
}