{
  "id": "durga_saptashati_chapter_3_sloka_22",
  "source": "Durga Saptashati - Chapter 3",
  "chapter": 3,
  "sloka_number": 22,
  "source_citation": "",
  "sloka_original": "కాంశ్చిత్తుండ ప్రహారేణ ఖురక్షేవైస్తథాప్పరాన్\nలాంగూలతాడితాంశ్చాన్యాంచృంగాభ్యాం చ విదారితాన్ || 22 ||",
  "pada_vibhaga": [
    {
      "word": "కాంశ్చిత్",
      "meaning": "కొంతమందిని",
      "grammar": "ద్వితీయా విభక్తి, బహువచనం, పుంలింగం, అనిర్దిష్ట సర్వనామం"
    },
    {
      "word": "తుండప్రహారేణ",
      "meaning": "ముఖం/మొన దెబ్బతో",
      "grammar": "తృతీయా విభక్తి, ఏకవచనం, పుంలింగం"
    },
    {
      "word": "ఖురక్షేపైః",
      "meaning": "గిట్టల విసురులతో, తన్నులతో",
      "grammar": "తృతీయా విభక్తి, బహువచనం, పుంలింగం"
    },
    {
      "word": "తథా",
      "meaning": "అలాగే",
      "grammar": "అవ్యయం"
    },
    {
      "word": "అపరాన్",
      "meaning": "ఇంకొంతమందిని",
      "grammar": "ద్వితీయా విభక్తి, బహువచనం, పుంలింగం"
    },
    {
      "word": "లాంగూలతాడితాన్",
      "meaning": "తోకతో కొట్టబడిన వారిని",
      "grammar": "ద్వితీయా విభక్తి, బహువచనం, పుంలింగం, క్త కృదంతం"
    },
    {
      "word": "చ",
      "meaning": "మరియు",
      "grammar": "అవ్యయం"
    },
    {
      "word": "అన్యాన్",
      "meaning": "మరికొందరిని",
      "grammar": "ద్వితీయా విభక్తి, బహువచనం, పుంలింగం"
    },
    {
      "word": "శృంగాభ్యాం",
      "meaning": "రెండు కొమ్ములతో",
      "grammar": "తృతీయా విభక్తి, ద్వివచనం, నపుంసకలింగం"
    },
    {
      "word": "చ",
      "meaning": "మరియు",
      "grammar": "అవ్యయం"
    },
    {
      "word": "విదారితాన్",
      "meaning": "చీల్చబడిన వారిని",
      "grammar": "ద్వితీయా విభక్తి, బహువచనం, పుంలింగం, క్త కృదంతం"
    }
  ],
  "anvaya": "మహిషాసురః కాంశ్చిత్ తుండప్రహారేణ, అపరాన్ ఖురక్షేపైః తథా, అన్యాన్ లాంగూలతాడితాన్ చ, శృంగాభ్యాం విదారితాన్ చ అకరోత్।",
  "tatparyam": {
    "english": "He struck some with his snout, others with his hooves; some he lashed with his tail, and others he tore with his horns.",
    "telugu": "మహిషాసురుడు కొందరిని తన తుండ దెబ్బతో, మరికొందరిని గిట్టల తన్నులతో, ఇంకొందరిని తోకతో కొట్టి, మరికొందరిని కొమ్ములతో చీల్చివేశాడు."
  },
  "samasas": [
    {
      "compound": "తుండప్రహారేణ",
      "type": "తృతీయా తత్పురుష సమాసం — తుండేన ప్రహారః"
    },
    {
      "compound": "ఖురక్షేపైః",
      "type": "తృతీయా తత్పురుష సమాసం — ఖురైః క్షేపాః"
    },
    {
      "compound": "లాంగూలతాడితాన్",
      "type": "తృతీయా తత్పురుష సమాసం — లాంగూలేన తాడితాః"
    }
  ],
  "sandhis": [
    {
      "joined_word": "కాంశ్చిత్",
      "split_words": "కాన్ + చిత్",
      "sandhi_rule": "అనుస్వార/శ్చుత్వ సంధి — న్ + చ → ంశ్చ"
    },
    {
      "joined_word": "తథాప్పరాన్",
      "split_words": "తథా + అపరాన్",
      "sandhi_rule": "సవర్ణదీర్ఘ సంధి — ఆ + అ → ఆ; పాఠరూపంలో ప్ప ద్విత్వప్రతీతి"
    },
    {
      "joined_word": "తాడితాంశ్చాన్యాన్",
      "split_words": "తాడితాన్ + చ + అన్యాన్",
      "sandhi_rule": "న్ + చ → ంశ్చ; చ + అ → చా, సవర్ణదీర్ఘ భావం"
    },
    {
      "joined_word": "చాన్యాన్",
      "split_words": "చ + అన్యాన్",
      "sandhi_rule": "సవర్ణదీర్ఘ సంధి — అ + అ → ఆ"
    }
  ],
  "alamkaram_chandas": "Chandas: అనుష్టుప్. Alamkara: సముచ్చయ వర్ణన ద్వారా భయానకరసోద్భావన."
}