{
  "id": "durga_saptashati_chapter_9_sloka_37",
  "source": "Durga Saptashati / Devi Mahatmyam",
  "chapter": "9",
  "sloka_number": "37",
  "source_citation": "",
  "sloka_original": "తతః సింహశ్చఖాదోగ్రం దంష్టాక్షుణ్ణశిరోధరాన్|\nఅసురాంస్తాంస్తథా కాలీ శివదూతీ తథాపరాన్ || 37 ||",
  "pada_vibhaga": [
    {
      "word": "తతః",
      "meaning": "తరువాత",
      "grammar": "అవ్యయం"
    },
    {
      "word": "సింహః",
      "meaning": "సింహం",
      "grammar": "ప్రథమా విభక్తి, ఏకవచనం, పుంలింగం"
    },
    {
      "word": "చఖాద",
      "meaning": "తినివేసింది / భక్షించింది",
      "grammar": "ఖాద్ ధాతువు, లిట్ లకారం, ప్రథమ పురుష, ఏకవచనం"
    },
    {
      "word": "ఉగ్రమ్",
      "meaning": "భయంకరంగా / ఘోరంగా",
      "grammar": "అవ్యయీభావసదృశ ప్రయోగం; విశేషణరూపం"
    },
    {
      "word": "దంష్ట్రాక్షుణ్ణశిరోధరాన్",
      "meaning": "దంతాలతో నలిగిన తలలు, మెడలు గలవారిని",
      "grammar": "సమస్తపదం, ద్వితీయా విభక్తి, బహువచనం, పుంలింగం"
    },
    {
      "word": "అసురాన్",
      "meaning": "అసురులను",
      "grammar": "ద్వితీయా విభక్తి, బహువచనం, పుంలింగం"
    },
    {
      "word": "తాన్",
      "meaning": "ఆ వారిని",
      "grammar": "సర్వనామం, ద్వితీయా విభక్తి, బహువచనం, పుంలింగం"
    },
    {
      "word": "తథా",
      "meaning": "అలాగే",
      "grammar": "అవ్యయం"
    },
    {
      "word": "కాలీ",
      "meaning": "కాళీ దేవి",
      "grammar": "ప్రథమా విభక్తి, ఏకవచనం, స్త్రీలింగం"
    },
    {
      "word": "శివదూతీ",
      "meaning": "శివదూతి దేవి",
      "grammar": "ప్రథమా విభక్తి, ఏకవచనం, స్త్రీలింగం"
    },
    {
      "word": "తథా",
      "meaning": "అలాగే",
      "grammar": "అవ్యయం"
    },
    {
      "word": "అపరాన్",
      "meaning": "ఇతరులను",
      "grammar": "ద్వితీయా విభక్తి, బహువచనం, పుంలింగం"
    }
  ],
  "anvaya": "తతః సింహః దంష్ట్రాక్షుణ్ణశిరోధరాన్ తాన్ అసురాన్ ఉగ్రం చఖాద। తథా కాలీ శివదూతీ చ అపరాన్ చఖాద।",
  "tatparyam": {
    "english": "Then the lion fiercely devoured those demons whose heads and necks had been crushed by its fangs. Likewise Kālī and Śivadūtī devoured the others.",
    "telugu": "తరువాత సింహం తన దంష్ట్రలచే తలలు, మెడలు నలిగిన ఆ అసురులను ఘోరంగా భక్షించింది. అలాగే కాళీ, శివదూతి ఇతర అసురులను భక్షించారు."
  },
  "samasas": [
    {
      "compound": "దంష్ట్రాక్షుణ్ణశిరోధరాన్",
      "type": "బహువ్రీహి సమాసం — దంష్ట్రాభిః క్షుణ్ణాని శిరాంసి ధరాశ్చ యేషాం తాన్"
    },
    {
      "compound": "శిరోధరాన్",
      "type": "ద్వంద్వ/ఇతరేతర భావం — శిరాంసి చ ధరాశ్చ"
    },
    {
      "compound": "శివదూతీ",
      "type": "షష్ఠీ తత్పురుష సమాసం — శివస్య దూతీ"
    }
  ],
  "sandhis": [
    {
      "joined_word": "సింహశ్చఖాద",
      "split_words": "సింహః + చఖాద",
      "sandhi_rule": "విసర్గసంధి — ః + చ → శ్చ."
    },
    {
      "joined_word": "చఖాదోగ్రం",
      "split_words": "చఖాద + ఉగ్రమ్",
      "sandhi_rule": "గుణస్వరసంధి — అ + ఉ → ఓ."
    },
    {
      "joined_word": "దంష్ట్రాక్షుణ్ణ",
      "split_words": "దంష్ట్రా + క్షుణ్ణ",
      "sandhi_rule": "సమాసాంతర్గత సవర్ణదీర్ఘసదృశ సంయోగం; ఆ తరువాత వ్యంజనం యథాతథం."
    },
    {
      "joined_word": "అసురాంస్తాన్",
      "split_words": "అసురాన్ + తాన్",
      "sandhi_rule": "అనుస్వార/పరసవర్ణసంధి — న్ + త్ ముందు ం/న్స్స్త్ సంయుక్తోచ్చారణ."
    },
    {
      "joined_word": "తథాపరాన్",
      "split_words": "తథా + అపరాన్",
      "sandhi_rule": "స్వరసంధి — ఆ + అ → ఆ."
    }
  ],
  "alamkaram_chandas": "అనుష్టుప్ ఛందస్సు. దంష్ట్రాక్షుణ్ణశిరోధర వర్ణనలో భయానకరస ప్రధాన చిత్రణ; వీరరసానుగుణ ఘోరవర్ణన ఉంది."
}