{
  "id": "durga_saptashati_chapter_6_sloka_13",
  "source": "Durga Saptashati / Devi Mahatmyam",
  "chapter": "6",
  "sloka_number": "13",
  "source_citation": "",
  "sloka_original": "ఇత్యుक्तః సోభ్యధావత్తామసురో ధూమ్రలోచనః|\nహుంకారేణైవ తం భస్మసాచ్చకారాంబికా తతః || 13 ||",
  "pada_vibhaga": [
    {
      "word": "ఇతి",
      "meaning": "ఇట్లు",
      "grammar": "అవ్యయం"
    },
    {
      "word": "ఉక్తః",
      "meaning": "చెప్పబడినవాడు",
      "grammar": "ప్రథమా విభక్తి, ఏకవచనం, పుంలింగం; క్తప్రత్యయాంతం; పాఠంలో మిశ్రలిపి ‘ఉक्तః’గా ఉంది"
    },
    {
      "word": "సః",
      "meaning": "అతడు",
      "grammar": "ప్రథమా విభక్తి, ఏకవచనం, పుంలింగ సర్వనామం"
    },
    {
      "word": "అభ్యధావత్",
      "meaning": "ఎదురుగా పరుగెత్తెను, దాడి చేసెను",
      "grammar": "అభి + √ధావ్, లఙ్ లకారం, ప్రథమ పురుషం, ఏకవచనం"
    },
    {
      "word": "తామ్",
      "meaning": "ఆమెపై, ఆమెను",
      "grammar": "ద్వితీయా విభక్తి, ఏకవచనం, స్త్రీలింగ సర్వనామం"
    },
    {
      "word": "అసురః",
      "meaning": "అసురుడు",
      "grammar": "ప్రథమా విభక్తి, ఏకవచనం, పుంలింగం"
    },
    {
      "word": "ధూమ్రలోచనః",
      "meaning": "ధూమ్రలోచనుడు",
      "grammar": "ప్రథమా విభక్తి, ఏకవచనం, పుంలింగం"
    },
    {
      "word": "హుంకారేణ",
      "meaning": "హుంకారముచేత",
      "grammar": "తృతీయా విభక్తి, ఏకవచనం, పుంలింగం"
    },
    {
      "word": "ఏవ",
      "meaning": "మాత్రమే",
      "grammar": "అవ్యయం"
    },
    {
      "word": "తమ్",
      "meaning": "అతనిని",
      "grammar": "ద్వితీయా విభక్తి, ఏకవచనం, పుంలింగ సర్వనామం"
    },
    {
      "word": "భస్మసాత్",
      "meaning": "భస్మరూపంగా",
      "grammar": "అవ్యయీభావసదృశ ప్రయోగం"
    },
    {
      "word": "చకార",
      "meaning": "చేసింది",
      "grammar": "√కృ, లిట్ లకారం, ప్రథమ పురుషం, ఏకవచనం"
    },
    {
      "word": "అంబికా",
      "meaning": "అంబికా దేవి",
      "grammar": "ప్రథమా విభక్తి, ఏకవచనం, స్త్రీలింగం"
    },
    {
      "word": "తతః",
      "meaning": "అప్పుడు",
      "grammar": "అవ్యయం"
    }
  ],
  "anvaya": "ఇతి ఉక్తః సః అసురః ధూమ్రలోచనః తాం అభ్యధావత్। తతః అంబికా హుంకారేణ ఏవ తం భస్మసాత్ చకార।",
  "tatparyam": {
    "english": "Thus addressed, the demon Dhumralochana rushed at her. Then Ambika reduced him to ashes by her mere humkara.",
    "telugu": "ఇలా చెప్పబడగానే ధూమ్రలోచనుడనే అసురుడు దేవిపై దూసుకెళ్లాడు. అప్పుడు అంబికా దేవి కేవలం తన హుంకారంతోనే అతనిని భస్మం చేసింది."
  },
  "samasas": [
    {
      "compound": "ధూమ్రలోచనః",
      "type": "బహువ్రీహి సమాసం — ధూమ్రే లోచనే యస్య సః"
    },
    {
      "compound": "భస్మసాత్",
      "type": "అవ్యయీభావ సమాససదృశ రూపం — భస్మత్వం ప్రాప్తం యథా"
    }
  ],
  "sandhis": [
    {
      "joined_word": "ఇత్యుక్తః",
      "split_words": "ఇతి + ఉక్తః",
      "sandhi_rule": "యణ్ సంధి — ఇ + ఉ వద్ద య్ ఆదేశం; పాఠంలో ‘ఇత్యుक्तః’గా మిశ్రలిపి ఉంది."
    },
    {
      "joined_word": "సోభ్యధావత్",
      "split_words": "సః + అభ్యధావత్",
      "sandhi_rule": "విసర్గ సంధి — అః + అ కలయికలో ఓ రూపం."
    },
    {
      "joined_word": "తామసురః",
      "split_words": "తామ్ + అసురః",
      "sandhi_rule": "మ్ + అ పదసంధి."
    },
    {
      "joined_word": "హుంకారేణైవ",
      "split_words": "హుంకారేణ + ఏవ",
      "sandhi_rule": "వృద్ధి సంధి — అ + ఏ = ఐ."
    },
    {
      "joined_word": "భస్మసాచ్చకార",
      "split_words": "భస్మసాత్ + చకార",
      "sandhi_rule": "శ్చుత్వ/చర్త్వ సంధి — త్ + చ వద్ద చ్ రూపసంబంధం."
    },
    {
      "joined_word": "చకారాంబికా",
      "split_words": "చకార + అంబికా",
      "sandhi_rule": "సవర్ణ దీర్ఘ సంధి — అ + అ = ఆ."
    }
  ],
  "alamkaram_chandas": "అనుష్టుప్ ఛందస్సు. దేవి హుంకారమాత్రంతో అసురుని నాశనం చేయడం అతిశయోక్తి-భావంతో వీరరసాన్ని వ్యక్తపరుస్తుంది."
}